agador/__init__.py
agador/credentials/__init__.py
agador/credentials/cyberark.py
agador/loaders.py
agador/mappers/__init__.py
agador/mappers/credentials.py
agador/mappers/save_to_db.py
agador/mappers/save_to_file.py
agador/nornir/__init__.py
agador/nornir/connection_options.py
agador/nornir/device_credentials.py
agador/nornir/logging.py
agador/nornir/processors.py
agador/nornir/runners.py
agador/nornir/tasks.py
agador/run.py
agador/run_with_schedule.py
agador/utils.py
agador-0.5.1.dist-info/METADATA
agador-0.5.1.dist-info/WHEEL
agador-0.5.1.dist-info/entry_points.txt
agador-0.5.1.dist-info/RECORD
