Metadata-Version: 2.3
Name: agador
Version: 0.5.1
Summary: UMnet network data gatherer
License: MIT
Author: Amy Liebowitz
Author-email: amylieb@umich.edu
Requires-Python: >=3.10,<4.0
Classifier: License :: OSI Approved :: MIT License
Classifier: Programming Language :: Python :: 3
Classifier: Programming Language :: Python :: 3.10
Classifier: Programming Language :: Python :: 3.11
Classifier: Programming Language :: Python :: 3.12
Classifier: Programming Language :: Python :: 3.13
Requires-Dist: cron-converter (>=1.2.1,<2.0.0)
Requires-Dist: gitpython (>=3.1.44,<4.0.0)
Requires-Dist: nornir (>=3.5.0)
Requires-Dist: nornir-netbox (>=0.3.0,<0.4.0)
Requires-Dist: pynetbox (>=7.5.0,<8.0.0)
Requires-Dist: python-decouple (>=3.8,<4.0)
Requires-Dist: python-slugify (>=8.0.4,<9.0.0)
Requires-Dist: pyyaml (>=6.0.2,<7.0.0)
Requires-Dist: umnet-db (>=0.5.0)
Requires-Dist: umnet-napalm (>=1.2.1)
